[{"time_interval_backup":"2.0:0","destination_path":"C:\\Users\\Utente\\Desktop","automatic_backup":true,"backup_name":"prova","notes":"","backup_count":2,"next_date_backup":"2024-11-16T09:14:42.013297600","start_path":"C:\\Users\\Utente\\Desktop\\AutoBackupProgram","creation_date":"2024-11-14T00:38:57.913908","last_backup":"2024-11-14T09:14:42.013297600","last_update_date":"2024-11-14T09:14:50.262976200"},{"time_interval_backup":null,"destination_path":"dsaasd","automatic_backup":false,"backup_name":"asd","notes":"","backup_count":0,"next_date_backup":null,"start_path":"yjfhjtgfhtg","creation_date":"2024-11-16T14:27:45.841538600","last_backup":null,"last_update_date":"2024-11-16T14:27:46.645729600"}]